{"code": "OK", "total": 1, "offset": 0, "items": [{"ean": "0884962161173", "title": "HP 650A (CE271A) Toner Cartridge  Cyan", "description": "Depend on Original HP 650A Toner Cartridges designed specifically for your HP printer.", "upc": "884962161173", "brand": "HP", "model": "HPCE271A", "color": "Cyan", "size": "", "dimension": "19.5 X 8.8 X 7.5 inches", "weight": "6 Pounds", "category": "Electronics > Print, Copy, Scan & Fax > Printer, Copier & Fax Machine Accessories > Printer Consumables", "currency": "CAD", "lowest_recorded_price": 0.77, "highest_recorded_price": 1029, "images": ["https://media.officedepot.com/images/t_extralarge%2Cf_auto/products/101247/101247_o01_101520.jpg", "https://i5.walmartimages.com/asr/11a4be0a-ac3e-4563-a86f-68c62022aca2_1.4362c06dbdaabd62f995313164e48c44.jpeg?odnHeight=450&odnWidth=450&odnBg=ffffff", "http://scene7.samsclub.com/is/image/samsclub/0088496216117_A?$img_size_211x208$", "http://www.123inkjets.com/media/catalog/product//6/6/6679.hp-oem-laser-cyan-ce271aoem.jpg", "http://www.adorama.com/images/large/IHPCE271A.JPG", "https://c1.neweggimages.com/ProductImageCompressAll640/28-115-874-V01.jpg", "http://site.unbeatablesale.com/img435/sprch38212.gif", "http://c.shld.net/rpx/i/s/pi/mp/23416/6179567417?src=http%3A%2F%2Fwww.techbuys.com%2Fprod_images%2Fpi80%2F%2F74084l.jpg&d=2c3fa3e14f38e64b7b7e60bf0bdbdf0b24765b09", "http://c.shld.net/rpx/i/s/i/spin/image/spin_prod_863278312", "https://www.staples.co.uk/content/images/product/GenesisExtraLarge/d5/4f/CNET.450f420328ea4388a5ea4b1a1e3ad54f.jpg"], "offers": [{"merchant": "Newegg Canada", "domain": "Newegg Canada", "title": "HP 650A LaserJet Toner Cartridge - Cyan", "currency": "CAD", "list_price": "", "price": 594.99, "shipping": "0.01", "condition": "New", "availability": "", "link": "https://www.upcitemdb.com/norob/alink/?id=y2v2331323x27444w2&tid=1&seq=1677267615&plt=8f1b368565dac841bc30a07194fe65f2", "updated_t": 1662162153}, {"merchant": "123Ink.ca", "domain": "123ink.ca", "title": "HP 650A CE271A cartouche de toner cyan", "currency": "CAD", "list_price": "", "price": 484.99, "shipping": "CA::Canada Post Expedited Parcel:484.99 CAD", "condition": "New", "availability": "", "link": "https://www.upcitemdb.com/norob/alink/?id=y2w2y2x2w24374b4y2&tid=1&seq=1677267615&plt=6c377c54ef65c410bda62b09413f2f0f", "updated_t": 1629255217}, {"merchant": "Staples", "domain": "staples.com", "title": "HP 650 (CE271A) Cyan Original Toner Cartridge for HP Color LaserJet Enterprise CP5525, M750 - At Staples", "currency": "", "list_price": "", "price": 448.99, "shipping": "", "condition": "New", "availability": "", "link": "https://www.upcitemdb.com/norob/alink/?id=y2o25323w253&tid=1&seq=1677267615&plt=6ab6a3ebf7cef16916d6faf70d4f53bb", "updated_t": 1579871162}, {"merchant": "Sam's Club", "domain": "samsclub.com", "title": "HP 650A Original Laser Jet Toner Cartridge, Select Color", "currency": "", "list_price": "", "price": 399.98, "shipping": "Free Shipping", "condition": "New", "availability": "Out of Stock", "link": "https://www.upcitemdb.com/norob/alink/?id=13p2y2v2x263e4d4&tid=1&seq=1677267615&plt=9ad7c36c5aa2d5a79b4eb46b66775f71", "updated_t": 1502832961}, {"merchant": "123Inkjets.com", "domain": "123Inkjets.com", "title": "HP 650A Toner", "currency": "", "list_price": 571.99, "price": 433.99, "shipping": "US::Ground:0.00 USD", "condition": "New", "availability": "", "link": "https://www.upcitemdb.com/norob/alink/?id=x2w263z2v203c4b4z2&tid=1&seq=1677267615&plt=2e2fc6249150db065633fda3b175c3e5", "updated_t": 1594780662}, {"merchant": "TheSource.ca", "domain": "thesource.ca", "title": "Cartouche d'encre LaserJet 650A CE271A de HP - cyan", "currency": "CAD", "list_price": "", "price": 599.99, "shipping": "", "condition": "New", "availability": "", "link": "https://www.upcitemdb.com/norob/alink/?id=u2s2y2z23303f454&tid=1&seq=1677267615&plt=85a9dba898fba2a76ec43f65d7449a7a", "updated_t": 1540975985}, {"merchant": "Shoplet.com", "domain": "shoplet.com", "title": "CE271A Toner", "currency": "", "list_price": "", "price": 399.97, "shipping": "", "condition": "New", "availability": "", "link": "https://www.upcitemdb.com/norob/alink/?id=u2u253x2w203d4d4&tid=1&seq=1677267615&plt=6e81c757cf05f081bdaab64d15f8c47e", "updated_t": 1570107660}, {"merchant": "Concord Supplies", "domain": "ConcordSupplies.com", "title": "HP 650A, (CE271A) Cyan Original LaserJet Toner Cartridge", "currency": "", "list_price": 583.21, "price": 499.41, "shipping": "", "condition": "New", "availability": "", "link": "https://www.upcitemdb.com/norob/alink/?id=u2v263v2y2y2a464&tid=1&seq=1677267615&plt=6c730acebc975b8628fa7cf1584070cf", "updated_t": 1500128147}, {"merchant": "Adorama", "domain": "adorama.com", "title": "HP CE271A Cyan Toner Cartridge", "currency": "", "list_price": "", "price": 407.99, "shipping": "Free Shipping", "condition": "New", "availability": "Out of Stock", "link": "https://www.upcitemdb.com/norob/alink/?id=u2w2x2t2y203b4b4&tid=1&seq=1677267615&plt=ff8d6e69b4e0d7c955e095d57b878465", "updated_t": 1474863701}, {"merchant": "Newegg.com", "domain": "newegg.com", "title": "HP 650A LaserJet Toner Cartridge - Cyan", "currency": "", "list_price": "", "price": 494.99, "shipping": "8.69", "condition": "New", "availability": "", "link": "https://www.upcitemdb.com/norob/alink/?id=v2p203w223037444z2&tid=1&seq=1677267615&plt=0b46577a2efd75d6bbd0d9e804464487", "updated_t": 1676857027}, {"merchant": "UnbeatableSale.com", "domain": "unbeatablesale.com", "title": "HEWCE271A Toner Cartridge- 15-000 Page YIeld- Cyan", "currency": "", "list_price": 640.51, "price": 492.7, "shipping": "US:::11.14 USD", "condition": "New", "availability": "", "link": "https://www.upcitemdb.com/norob/alink/?id=v2o243231313d464&tid=1&seq=1677267615&plt=54edad910b2669d0c84f6c3ba2e97a8d", "updated_t": 1677239595}, {"merchant": "DollarDays", "domain": "dollardays.com", "title": "Toner Cartridge, 15,000 Page YIeld, Cyan. .", "currency": "", "list_price": "", "price": 661.48, "shipping": "", "condition": "New", "availability": "", "link": "https://www.upcitemdb.com/norob/alink/?id=v2q2x2y24303b4d4&tid=1&seq=1677267615&plt=d1a5293d89fb58813af6e4ae449368b4", "updated_t": 1435972478}, {"merchant": "PCM", "domain": "pcm.com", "title": "HP Inc. CE271A 650A - Cyan - original - LaserJet - toner cartridge (CE271A) - for Color LaserJet Enterprise CP5520  CP5525  M750", "currency": "", "list_price": "", "price": 448.99, "shipping": "US::UPS Ground:21.63 USD", "condition": "New", "availability": "", "link": "https://www.upcitemdb.com/norob/alink/?id=v2q2x2u243539454s2&tid=1&seq=1677267615&plt=be07eb6018f80521ccaeade1ccc97d84", "updated_t": 1584440085}, {"merchant": "Sears", "domain": "sears.com", "title": "650A Cyan Laser Toner Cartridge", "currency": "", "list_price": "", "price": 369.48, "shipping": "", "condition": "New", "availability": "", "link": "https://www.upcitemdb.com/norob/alink/?id=v2r2x213x2z2e454&tid=1&seq=1677267615&plt=8f24f3674272c32b99843ddb17c077f5", "updated_t": 1481114279}, {"merchant": "Kmart", "domain": "kmart.com", "title": "HP 650A Cyan Laser Toner Cartridge", "currency": "", "list_price": "", "price": 401.23, "shipping": "8.20", "condition": "New", "availability": "", "link": "https://www.upcitemdb.com/norob/alink/?id=y2t203w2z233c4a4&tid=1&seq=1677267615&plt=348b3aae6ea26cb3b6c258934c12e800", "updated_t": 1481134342}, {"merchant": "MacMall", "domain": "macmall.com", "title": "HP Inc. CE271A Color LaserJet CE271A Cyan Print Cartridge", "currency": "", "list_price": "", "price": 448.99, "shipping": "US::UPS Ground:15.85 USD", "condition": "New", "availability": "", "link": "https://www.upcitemdb.com/norob/alink/?id=v2q2x2z2z2x264a4s2&tid=1&seq=1677267615&plt=929eeda649d0cbf2af06f6051f83bfa7", "updated_t": 1587658160}, {"merchant": "Office Depot", "domain": "officedepot.com", "title": "HP 650A Cyan Toner Cartridge, CE271A", "currency": "", "list_price": "", "price": 494.89, "shipping": "US:::9.95 USD", "condition": "New", "availability": "", "link": "https://www.upcitemdb.com/norob/alink/?id=v2w203w21303e454&tid=1&seq=1677267615&plt=4d7901c16d94757b5a99011d38146b91", "updated_t": 1676894283}, {"merchant": "Office Max", "domain": "officemax.com", "title": "HP 650A Cyan Original LaserJet Toner Cartridge (CE271A)", "currency": "", "list_price": "", "price": 407.99, "shipping": "Free Shipping", "condition": "New", "availability": "Out of Stock", "link": "https://www.upcitemdb.com/norob/alink/?id=v2w213v21353c4b4&tid=1&seq=1677267615&plt=c7e146e3a9b6a18996ce3e0648bffbcd", "updated_t": 1481140967}, {"merchant": "Mwave", "domain": "mwave.com", "title": "Hewlett Packard CE271A OEM Toner - HP 650A Color LJ CP5520 Series CP5525n CP5525dn CP5525xh M750 ColorSphere Print Cartridge Cyan (15000 Yield) (60/Pallet)", "currency": "", "list_price": 487.89, "price": 435.62, "shipping": "", "condition": "New", "availability": "", "link": "https://www.upcitemdb.com/norob/alink/?id=y2w243z2z263e454&tid=1&seq=1677267615&plt=ffc59d4f6183770c625246202333eff9", "updated_t": 1433058015}, {"merchant": "Staples UK", "domain": "staples.co.uk", "title": "HP 650A Toner Cartridge, CE271A, Cyan", "currency": "GBP", "list_price": "", "price": 406.8, "shipping": "UK:::0.00 GBP", "condition": "New", "availability": "", "link": "https://www.upcitemdb.com/norob/alink/?id=v2s2x20333239474s2&tid=1&seq=1677267615&plt=33f5f3941f38e44c8aed3ba13494a767", "updated_t": 1618056527}, {"merchant": "Rakuten(Buy.com)", "domain": "rakuten.com", "title": "Hewlett-Packard HEWCE271A Toner Cartridge, 15,000 Page YIeld, Cyan", "currency": "", "list_price": "", "price": 448.99, "shipping": "", "condition": "New", "availability": "", "link": "https://www.upcitemdb.com/norob/alink/?id=x2o213u21303b494&tid=1&seq=1677267615&plt=f24ece35efafcdb28a81cbc4d4755213", "updated_t": 1598286415}, {"merchant": "HOWARDstore", "domain": "howardstore.com", "title": "HP 650A", "currency": "", "list_price": "", "price": 407.99, "shipping": "Free Shipping", "condition": "New", "availability": "Out of Stock", "link": "https://www.upcitemdb.com/norob/alink/?id=x2o2y2w2v253f484&tid=1&seq=1677267615&plt=ff4dbd5e213a960e7404b85bebd2a0cc", "updated_t": 1439674225}, {"merchant": "pcRUSH.com", "domain": "pcrush.com", "title": "CE271A Toner Cartridge - Cyan", "currency": "", "list_price": 533, "price": 366.71, "shipping": "13.28", "condition": "New", "availability": "", "link": "https://www.upcitemdb.com/norob/alink/?id=x2q263v213336484&tid=1&seq=1677267615&plt=cb54bbbd5ac8baecbbf00abdbc679c8d", "updated_t": 1449244013}, {"merchant": "HP.com", "domain": "hp.com", "title": "HP 650A Cyan Original LaserJet Toner Cartridge", "currency": "", "list_price": "", "price": 407.99, "shipping": "Free Shipping", "condition": "New", "availability": "Out of Stock", "link": "https://www.upcitemdb.com/norob/alink/?id=x2r263u223x2d4d4&tid=1&seq=1677267615&plt=0df03e5ad09a39c1a4c9342f9f2873d6", "updated_t": 1478145961}, {"merchant": "Wal-Mart.com", "domain": "walmart.com", "title": "HP 650A (CE271A) Toner Cartridge  Cyan", "currency": "", "list_price": "", "price": 470.89, "shipping": "Free Shipping", "condition": "New", "availability": "Out of Stock", "link": "https://www.upcitemdb.com/norob/alink/?id=y2s2x2031353b4a4&tid=1&seq=1677267615&plt=943b24d174772a21ee7d0e59cde8cfed", "updated_t": 1663533642}, {"merchant": "TigerDirect", "domain": "tigerdirect.com", "title": "HP 650A Cyan Original Toner Cartridge - Laser 1-pack Up to 15000 Pages", "currency": "", "list_price": "", "price": 494.99, "shipping": ":::0.00 USD", "condition": "New", "availability": "", "link": "https://www.upcitemdb.com/norob/alink/?id=y2s263x233137464&tid=1&seq=1677267615&plt=8788e0e27dd716c46b4488fd983c54de", "updated_t": 1677207731}, {"merchant": "InkCartridges.com", "domain": "inkcartridges.com", "title": "HP 650A Toner", "currency": "", "list_price": "", "price": 443.99, "shipping": "US::Ground:0.00 USD", "condition": "New", "availability": "", "link": "https://www.upcitemdb.com/norob/alink/?id=x2x2x2v21363d454v2&tid=1&seq=1677267615&plt=eebaaee5bdd5e6b5a04cd1c72a8e9205", "updated_t": 1594741861}, {"merchant": "databazaar.com", "domain": "databazaar.com", "title": "HP CE271A Cyan Toner Cartridge  HP 650A", "currency": "", "list_price": "", "price": 357.87, "shipping": "Free Shipping", "condition": "New", "availability": "", "link": "https://www.upcitemdb.com/norob/alink/?id=y2w243y2w2z2d4c4&tid=1&seq=1677267615&plt=3cb993cb3fa9f49ca8a1b0e0f5def12f", "updated_t": 1485907857}, {"merchant": "Hook Bag", "domain": "hookbag.com", "title": "Toner Cartridge 15 000 Page YIeld Cyan H3C06KNF5-2709", "currency": "CAD", "list_price": "", "price": 410.28, "shipping": "Free Shipping", "condition": "New", "availability": "", "link": "https://www.upcitemdb.com/norob/alink/?id=y2x213u233037484&tid=1&seq=1677267615&plt=0789cbb5f05438f611dcf950bccf7368", "updated_t": 1427562705}, {"merchant": "Alibris UK", "domain": "alibris.co.uk", "title": "HP 650A Original Laser Jet Toner Cartridge, Select Color", "currency": "GBP", "list_price": "", "price": 369.98, "shipping": "Free Shipping", "condition": "New", "availability": "Out of Stock", "link": "https://www.upcitemdb.com/norob/alink/?id=13p203u23343e4d4&tid=1&seq=1677267615&plt=b4c58ed029e835e6ce8f75611b77c34e", "updated_t": 1413572482}, {"merchant": "Zuma Office Supply", "domain": "zumaoffice.com", "title": "650A, (CE271A) Cyan Original LaserJet Toner Cartridge", "currency": "", "list_price": "", "price": 379.98, "shipping": "", "condition": "New", "availability": "", "link": "https://www.upcitemdb.com/norob/alink/?id=u2r263u203039474s2&tid=1&seq=1677267615&plt=e742f82bfd0f010048ec5632f83f9b21", "updated_t": 1452702647}, {"merchant": "Quill.com", "domain": "quill.com", "title": "HP 650A Cyan Standard Yield Toner Cartridge (CE271A) | Quill", "currency": "", "list_price": "", "price": 494.99, "shipping": "", "condition": "New", "availability": "", "link": "https://www.upcitemdb.com/norob/alink/?id=x2x243u2x2539464u2&tid=1&seq=1677267615&plt=75b067630ddbdb66f510879333189bb0", "updated_t": 1676895174}, {"merchant": "11 Main", "domain": "11Main.com", "title": "Hewlett-Packard HEWCE271A Toner Cartridge, 15,000 Page YIeld, Cyan", "currency": "", "list_price": "", "price": 409, "shipping": "", "condition": "New", "availability": "", "link": "https://www.upcitemdb.com/norob/alink/?id=u2q2532313z2e484q2&tid=1&seq=1677267615&plt=0703689724d911d8d5afe42a233f8f39", "updated_t": 1437730496}, {"merchant": "TigerDirect Canada", "domain": "tigerdirect.ca", "title": "HP CE270A CE271A CE272A CE273A Toner", "currency": "", "list_price": "", "price": 484.99, "shipping": "", "condition": "New", "availability": "", "link": "https://www.upcitemdb.com/norob/alink/?id=w2w203v2x203f4c4s2&tid=1&seq=1677267615&plt=0289438a42f56d4302e883ba79c4902c", "updated_t": 1560237859}, {"merchant": "", "domain": "", "title": "Hp CE271A Toner Cartridge, Cyan", "currency": "", "list_price": "", "price": 399, "shipping": "Free Shipping", "condition": "New", "availability": "Out of Stock", "link": "https://www.upcitemdb.com/norob/alink/?id=v2u2x2u233x2b4b4v2&tid=1&seq=1677267615&plt=31431e793ac3455c558e213fa7edd359", "updated_t": 1501970290}, {"merchant": "Newegg Canada", "domain": "newegg.ca", "title": "HP CE271A Toner Cartridge Cyan", "currency": "CAD", "list_price": "", "price": 473.91, "shipping": "", "condition": "New", "availability": "", "link": "https://www.upcitemdb.com/norob/alink/?id=v2o253t2z2z2c484v2&tid=1&seq=1677267615&plt=1c4959c268aa31cff954eea084cc4bcd", "updated_t": 1560236194}, {"merchant": "Newegg Business", "domain": "neweggbusiness.com", "title": "HP CE271A Toner Cartridge Cyan", "currency": "", "list_price": "", "price": 476.95, "shipping": "Free Shipping", "condition": "New", "availability": "Out of Stock", "link": "https://www.upcitemdb.com/norob/alink/?id=v2o2632343z2a4a4z2&tid=1&seq=1677267615&plt=6d8a5f1b76c2c76e28f2596e15a9a86d", "updated_t": 1526489831}, {"merchant": "Pricefalls.com", "domain": "pricefalls.com", "title": "Hp 650a Cyan Original Laserjet Toner Cartridge Ce271a For Color Laserjet Enterprise Cp5520, Cp5525, M750", "currency": "", "list_price": "", "price": 596.49, "shipping": "", "condition": "New", "availability": "", "link": "https://www.upcitemdb.com/norob/alink/?id=v2q2531333x2a4b4s2&tid=1&seq=1677267615&plt=b9da5417a486ca3857917d8886cd0a58", "updated_t": 1484918401}, {"merchant": "Mansion Schools", "domain": "mansionschools.com", "title": "Crtdg-clj Cp5525-cyn-15k -hewce271a - 1409366 - Business Machines Ink & Toner", "currency": "", "list_price": 957.39, "price": 825.34, "shipping": "", "condition": "New", "availability": "", "link": "https://www.upcitemdb.com/norob/alink/?id=v2r203v223z2b454s2&tid=1&seq=1677267615&plt=24c1d05e1c76f1ee4a29a70e6b71a0e8", "updated_t": 1485890877}, {"merchant": "Shopper+", "domain": "shopperplus.ca", "title": "HP 650A CE271A cartouche de toner originale cyan", "currency": "CAD", "list_price": "", "price": 484.99, "shipping": "CA::Canada Post Expedited Parcel:484.99 CAD", "condition": "New", "availability": "", "link": "https://www.upcitemdb.com/norob/alink/?id=x2w263y243z28464v2&tid=1&seq=1677267615&plt=11973371707602f39baf06565191869c", "updated_t": 1587954859}, {"merchant": "US Salon Supply LLC", "domain": "ussalonsupply.com", "title": "HP HP 650A, (CE271A) Cyan Original LaserJet Toner Cartridge", "currency": "", "list_price": 555.44, "price": 416.15, "shipping": "", "condition": "New", "availability": "", "link": "https://www.upcitemdb.com/norob/alink/?id=v2r2z223x2336484w2&tid=1&seq=1677267615&plt=b35d1a41afac781ab5dc9d6fe64678df", "updated_t": 1485000997}, {"merchant": "OnBuy.com", "domain": "onbuy.com", "title": "HP CE271A (650A) Toner cyan, 15K pages", "currency": "GBP", "list_price": "", "price": 356.27, "shipping": "GB:Mainland UK:Standard:0.00 GBP", "condition": "New", "availability": "", "link": "https://www.upcitemdb.com/norob/alink/?id=x2x2y2x24323e4d4s2&tid=1&seq=1677267615&plt=0e196f3551d0670854e238e11e1e1c0f", "updated_t": 1571464518}], "asin": "B004C43JAS", "elid": "275658624213"}]}